Metadata-Version: 2.1
Name: PyOSCmd
Version: 0.1
Summary: PySysCmd是一个用于开发终端PY命令行的第三方库，简单，易用。
Home-page: https://github.com/PYmili
Author: PYmili
Author-email: mc2005wj@163.com
Maintainer: PYmili
Maintainer-email: mc2005wj@163.com
License: MIT License
Classifier: Development Status :: 3 - Alpha
Classifier: Intended Audience :: Developers
Classifier: Topic :: Software Development :: Build Tools
Classifier: License :: OSI Approved :: MIT License
Classifier: Programming Language :: Python :: 3
Requires-Python: >=3.8
License-File: LICENSE
